{
	"ImportPath": "github.com/mong0520/ChainChronicleGo",
	"GoVersion": "go1.10",
	"GodepVersion": "v80",
	"Deps": [
		{
			"ImportPath": "github.com/deckarep/golang-set",
			"Comment": "v1.7",
			"Rev": "1d4478f51bed434f1dadf96dcd9b43aabac66795"
		},
		{
			"ImportPath": "github.com/goinggo/mapstructure",
			"Rev": "194205d9b4a98eff86d4e8d3c0dfe87dea59ef81"
		},
		{
			"ImportPath": "github.com/icza/dyno",
			"Rev": "15f794d2c82a97f44c27c18fe7d1fbea385fe40b"
		},
		{
			"ImportPath": "github.com/jessevdk/go-flags",
			"Comment": "v1.3.0-5-gf88afde",
			"Rev": "f88afde2fa19a30cf50ba4b05b3d13bc6bae3079"
		},
		{
			"ImportPath": "github.com/oleiade/reflections",
			"Comment": "0.1.2-12-g0e86b3c",
			"Rev": "0e86b3c98b2ff33e30c85cfe97d9a63d439fe7eb"
		},
		{
			"ImportPath": "github.com/op/go-logging",
			"Comment": "v1-7-g970db52",
			"Rev": "970db520ece77730c7e4724c61121037378659d9"
		},
		{
			"ImportPath": "github.com/robfig/config",
			"Rev": "0f78529c8c7e3e9a25f15876532ecbc07c7d99e6"
		},
		{
			"ImportPath": "github.com/satori/go.uuid",
			"Comment": "v1.2.0-4-g36e9d2e",
			"Rev": "36e9d2ebbde5e3f13ab2e25625fd453271d6522e"
		},
		{
			"ImportPath": "golang.org/x/net/proxy",
			"Rev": "5ccada7d0a7ba9aeb5d3aca8d3501b4c2a509fec"
		},
		{
			"ImportPath": "gopkg.in/mgo.v2",
			"Comment": "r2016.08.01-5-g3f83fa5",
			"Rev": "3f83fa5005286a7fe593b055f0d7771a7dce4655"
		},
		{
			"ImportPath": "gopkg.in/mgo.v2/bson",
			"Comment": "r2016.08.01-5-g3f83fa5",
			"Rev": "3f83fa5005286a7fe593b055f0d7771a7dce4655"
		},
		{
			"ImportPath": "gopkg.in/mgo.v2/internal/json",
			"Comment": "r2016.08.01-5-g3f83fa5",
			"Rev": "3f83fa5005286a7fe593b055f0d7771a7dce4655"
		},
		{
			"ImportPath": "gopkg.in/mgo.v2/internal/sasl",
			"Comment": "r2016.08.01-5-g3f83fa5",
			"Rev": "3f83fa5005286a7fe593b055f0d7771a7dce4655"
		},
		{
			"ImportPath": "gopkg.in/mgo.v2/internal/scram",
			"Comment": "r2016.08.01-5-g3f83fa5",
			"Rev": "3f83fa5005286a7fe593b055f0d7771a7dce4655"
		}
	]
}
